{
  "os":  "Linux-6.1.159-1.el9.elrepo.x86_64-x86_64-with-glibc2.34",
  "python":  "CPython 3.13.11",
  "startedAt":  "2026-01-09T12:22:01.021249Z",
  "program":  "-m pneumoniaclassifier.train",
  "git":  {
    "remote":  "https://github.com/ariansumak/MLOPS_105.git",
    "commit":  "3a1effda84d6877729375f95cc942fca89900a23"
  },
  "email":  "s253819@dtu.dk",
  "root":  "/zhome/8a/1/224071/code/MLOPS_105",
  "host":  "gbarlogin1",
  "executable":  "/zhome/8a/1/224071/code/MLOPS_105/.venv/bin/python3",
  "cpu_count":  64,
  "cpu_count_logical":  64,
  "disk":  {
    "/":  {
      "total":  "76817485824",
      "used":  "7771619328"
    }
  },
  "memory":  {
    "total":  "1081355767808"
  },
  "writerId":  "2us41xlno8nlyg98h5xmuzg6qdug9spi"
}